stonefish/__init__.py
stonefish/stonefish.cpython-310.sfc
stonefish-0.6.6.dist-info/METADATA
stonefish-0.6.6.dist-info/RECORD
stonefish-0.6.6.dist-info/WHEEL
stonefish-0.6.6.dist-info/entry_points.txt
stonefish-0.6.6.dist-info/top_level.txt
stonefish-0.6.6.dist-info/RECORD