Metadata-Version: 2.4
Name: stonefish
Version: 0.6.6
Summary: Python code protection and licensing
Author-email: Nico Schlömer <nico.schloemer@gmail.com>
License-Expression: LicenseRef-Proprietary
Project-URL: Homepage, https://github.com/stonefish-dev/stonefish
Project-URL: Issues, https://github.com/stonefish-dev/stonefish/issues
Classifier: Development Status :: 5 - Production/Stable
Classifier: Operating System :: OS Independent
Classifier: Programming Language :: Python
Classifier: Programming Language :: Python :: 3 :: Only
Classifier: Programming Language :: Python :: 3.10
Classifier: Programming Language :: Python :: 3.11
Classifier: Programming Language :: Python :: 3.12
Classifier: Programming Language :: Python :: 3.13
Classifier: Programming Language :: Python :: 3.14
Classifier: Topic :: Utilities
Requires-Python: >=3.10
Requires-Dist: cryptography
Requires-Dist: isodate
Requires-Dist: jsonschema[format-nongpl]
Requires-Dist: libcst>=0.4.6
Requires-Dist: packaging
Requires-Dist: python-package-info
Requires-Dist: pyyaml
Requires-Dist: rich>=11
Requires-Dist: rich-argparse
Requires-Dist: setuptools>=61
Requires-Dist: stonefish-license-manager>=0.5.24
Requires-Dist: stonefish-runtime>=0.3.5
Requires-Dist: tomli; python_version < "3.11"
Requires-Dist: stonefish_runtime>=0.3.5
